logvista/__init__.py
logvista/level.py
logvista/logvista.py
logvista/configs/__init__.py
logvista/configs/file_config.py
logvista/configs/logvista_config.py
logvista/configs/stream_config.py
logvista/handlers/__init__.py
logvista/handlers/logvista_handler.py
python_logvista-0.1.6.dist-info/LICENSE
python_logvista-0.1.6.dist-info/METADATA
python_logvista-0.1.6.dist-info/WHEEL
python_logvista-0.1.6.dist-info/top_level.txt
python_logvista-0.1.6.dist-info/RECORD
