Metadata-Version: 2.1
Name: python-logvista
Version: 0.1.6
Summary: LogVista SDK for Python
Author-email: Dencyuman <t.tanaka@triggerhack.com>
License: Apache License
License-File: LICENSE
Requires-Dist: psutil
Requires-Dist: pytz
